cl_ext/__init__.py
cl_ext/lang/__init__.py
cl_ext/lang/lang.py
cl_ext.lang-0.1.0.dist-info/LICENSE
cl_ext.lang-0.1.0.dist-info/METADATA
cl_ext.lang-0.1.0.dist-info/WHEEL
cl_ext.lang-0.1.0.dist-info/entry_points.txt
cl_ext.lang-0.1.0.dist-info/top_level.txt
cl_ext.lang-0.1.0.dist-info/RECORD
