Metadata-Version: 2.1
Name: cl-ext.lang
Version: 0.1.0
Summary: .lang parser for compare-locales
Home-page: UNKNOWN
Author: Axel Hecht
Author-email: axel@mozilla.com
License: UNKNOWN
Platform: any
Requires-Python: >=2.7, !=3.0.*, !=3.1.*, !=3.2.*, !=3.3.*, !=3.4.*, <4
Requires-Dist: parsimonious
Requires-Dist: compare-locales
